piservod/PiServoD.py
piservod/Servo.py
piservod/__init__.py
piservod/errors.py
piservod-0.1.2.dist-info/licenses/LICENSE.md
piservod-0.1.2.dist-info/METADATA
piservod-0.1.2.dist-info/WHEEL
piservod-0.1.2.dist-info/top_level.txt
piservod-0.1.2.dist-info/RECORD
