Metadata-Version: 2.4
Name: piservod
Version: 0.1.2
Summary: Python bindings for piservod - software PWM daemon for controlling servos on Raspberry Pi
Author-email: "Chris L." <stylesuxx@gmail.com>
Maintainer-email: "Chris L." <stylesuxx@gmail.com>
License: MIT
Project-URL: Homepage, https://github.com/stylesuxx/piservod
Project-URL: Repository, https://github.com/stylesuxx/piservod-python
Project-URL: Issues, https://github.com/stylesuxx/piservod-python/issues
Project-URL: Documentation, https://github.com/stylesuxx/piservod-python#readme
Keywords: raspberry-pi,servo,pwm,robotics,gpio,piservod
Classifier: Development Status :: 3 - Alpha
Classifier: Intended Audience :: Developers
Classifier: Topic :: System :: Hardware
Classifier: Topic :: Software Development :: Libraries :: Python Modules
Classifier: License :: OSI Approved :: MIT License
Classifier: Programming Language :: Python :: 3
Classifier: Programming Language :: Python :: 3.7
Classifier: Programming Language :: Python :: 3.8
Classifier: Programming Language :: Python :: 3.9
Classifier: Programming Language :: Python :: 3.10
Classifier: Programming Language :: Python :: 3.11
Classifier: Programming Language :: Python :: 3.12
Classifier: Operating System :: POSIX :: Linux
Requires-Python: >=3.7
License-File: LICENSE.md
Provides-Extra: dev
Requires-Dist: pytest>=7.0; extra == "dev"
Requires-Dist: pytest-cov>=4.0; extra == "dev"
Requires-Dist: black>=22.0; extra == "dev"
Requires-Dist: flake8>=5.0; extra == "dev"
Requires-Dist: mypy>=0.990; extra == "dev"
Requires-Dist: build>=0.10.0; extra == "dev"
Requires-Dist: twine>=4.0.0; extra == "dev"
Dynamic: license-file
